syneto_openapi_themes/__init__.py
syneto_openapi_themes/brand.py
syneto_openapi_themes/elements.py
syneto_openapi_themes/fastapi_integration.py
syneto_openapi_themes/rapidoc.py
syneto_openapi_themes/redoc.py
syneto_openapi_themes/scalar.py
syneto_openapi_themes/swagger.py
syneto_openapi_themes-0.2.3.dist-info/LICENSE
syneto_openapi_themes-0.2.3.dist-info/METADATA
syneto_openapi_themes-0.2.3.dist-info/WHEEL
syneto_openapi_themes-0.2.3.dist-info/RECORD
