Metadata-Version: 2.3
Name: syneto-openapi-themes
Version: 0.2.3
Summary: Syneto-branded themes and utilities for OpenAPI documentation tools
License: MIT
Keywords: openapi,fastapi,rapidoc,swagger,redoc,syneto,themes
Author: Syneto
Author-email: dev@syneto.net
Requires-Python: >=3.9.2,<4.0.0
Classifier: Development Status :: 4 - Beta
Classifier: Framework :: FastAPI
Classifier: Intended Audience :: Developers
Classifier: License :: OSI Approved :: MIT License
Classifier: Operating System :: OS Independent
Classifier: Programming Language :: Python :: 3
Classifier: Programming Language :: Python :: 3.10
Classifier: Programming Language :: Python :: 3.11
Classifier: Programming Language :: Python :: 3.12
Classifier: Programming Language :: Python :: 3.13
Classifier: Programming Language :: Python :: 3.9
Classifier: Topic :: Documentation
Classifier: Topic :: Internet :: WWW/HTTP
Classifier: Topic :: Software Development :: Libraries :: Python Modules
Provides-Extra: all
Provides-Extra: fastapi
Requires-Dist: cryptography (>=45.0.4,<46.0.0)
Requires-Dist: fastapi (>=0.115.12,<0.116.0) ; extra == "fastapi" or extra == "all"
Requires-Dist: jinja2 (>=3.1.0,<4.0.0)
Requires-Dist: openapipages (>=0.1.2,<0.2.0)
Requires-Dist: pip (>=25.1.1,<26.0.0)
Project-URL: Documentation, https://github.com/syneto/syneto-openapi-themes
Project-URL: Homepage, https://github.com/syneto/syneto-openapi-themes
Project-URL: Repository, https://github.com/syneto/syneto-openapi-themes
